container_utils/ContainerUtils.py
container_utils/ImageUtils.py
container_utils/__init__.py
container_utils-0.0.1.dist-info/LICENSE
container_utils-0.0.1.dist-info/METADATA
container_utils-0.0.1.dist-info/WHEEL
container_utils-0.0.1.dist-info/top_level.txt
container_utils-0.0.1.dist-info/zip-safe
container_utils-0.0.1.dist-info/RECORD
