Metadata-Version: 2.1
Name: container-utils
Version: 0.0.1
Summary: Utility functionality for working with Docker containers
Home-page: http://github.com/adamrehn/container-utils
Author: Adam Rehn
Author-email: adam@adamrehn.com
License: MIT
Keywords: docker container utilities
Platform: UNKNOWN
Classifier: License :: OSI Approved :: MIT License
Classifier: Programming Language :: Python :: 3.5
Classifier: Programming Language :: Python :: 3.6
Classifier: Programming Language :: Python :: 3.7
Classifier: Programming Language :: Python :: 3.8
Classifier: Topic :: Software Development :: Build Tools
Classifier: Environment :: Console
Requires-Python: >=3.5
Requires-Dist: docker (>=3.7.0)
Requires-Dist: setuptools (>=38.6.0)
Requires-Dist: twine (>=1.11.0)
Requires-Dist: wheel (>=0.31.0)
